tuesday/File.py
tuesday/__init__.py
tuesday/localweather.py
tuesday/search.py
tuesday/searchwiki.py
tuesday/sendmail.py
tuesday/social.py
tuesday/speech.py
tuesday/system.py
tuesday/websites.py
tuesday/whatisthetime.py
tuesday-3.0.0.dist-info/LICENSE
tuesday-3.0.0.dist-info/METADATA
tuesday-3.0.0.dist-info/WHEEL
tuesday-3.0.0.dist-info/top_level.txt
tuesday-3.0.0.dist-info/RECORD
