Metadata-Version: 2.1
Name: tuesday
Version: 3.0.0
Summary: A python package for automation
Home-page: https://github.com/om9999/Tuesday
Author: OSD999
Author-email: osdev99@gmail.com
License: UNKNOWN
Platform: UNKNOWN
Classifier: Programming Language :: Python :: 3.7
Classifier: License :: OSI Approved :: MIT License
Classifier: Operating System :: OS Independent
Requires-Python: >=3
Requires-Dist: selenium
Requires-Dist: wikipedia
Requires-Dist: pyttsx3
Requires-Dist: speechRecognition
Requires-Dist: requests
Requires-Dist: PyAudio
Requires-Dist: geocoder
